setup.cfg
setup.py
flowthings/__init__.py
flowthings/api.py
flowthings/builders.py
flowthings/default.py
flowthings/exceptions.py
flowthings/services.py
flowthings/utils.py
flowthings.egg-info/PKG-INFO
flowthings.egg-info/SOURCES.txt
flowthings.egg-info/dependency_links.txt
flowthings.egg-info/requires.txt
flowthings.egg-info/top_level.txt