Metadata-Version: 1.0
Name: flowthings
Version: 1.0.1
Summary: API client for the flowthings.io platform
Home-page: https://github.com/flowthings/python-client
Author: flowthings
Author-email: dev@flowthings.io
License: UNKNOWN
Platform: UNKNOWN
